asterisksecurity/__init__.py
asterisksecurity/console.py
asterisksecurity/encryption.py
asterisksecurity/error.py
asterisksecurity/setting.json
asterisk_security-0.1.4.1203.2254.dist-info/LICENSE
asterisk_security-0.1.4.1203.2254.dist-info/METADATA
asterisk_security-0.1.4.1203.2254.dist-info/WHEEL
asterisk_security-0.1.4.1203.2254.dist-info/entry_points.txt
asterisk_security-0.1.4.1203.2254.dist-info/top_level.txt
asterisk_security-0.1.4.1203.2254.dist-info/RECORD
