Metadata-Version: 2.1
Name: asterisk-security
Version: 0.1.4.1203.2254
Summary: Security module for asterisk series.
Author: Shan,Tian
Author-email: geoshan@163.com
License: Apache License 2.0
Keywords: encrypt,decrypt,security,asterisk
Platform: Independent
Classifier: Development Status :: 4 - Beta
Classifier: Topic :: Utilities
Classifier: License :: OSI Approved :: Apache Software License
Classifier: Environment :: Console
Classifier: Intended Audience :: Developers
Classifier: Operating System :: OS Independent
Classifier: Programming Language :: Python :: 3 :: Only
Classifier: Programming Language :: Python :: 3.10
Requires-Python: >=3.10.0
License-File: LICENSE
Requires-Dist: colorama>=0.4.4
Requires-Dist: pyDes>=2.0.1
Requires-Dist: Deprecated>=1.2.13
